import_watch/__init__.py
import_watch/_cyclic_import_package/__init__.py
import_watch/_cyclic_import_package/a.py
import_watch/_cyclic_import_package/b.py
import_watch/_cyclic_import_package/codec.py
import_watch/_cyclic_import_package/error.py
import_watch/_cyclic_import_package/loader.py
import_watch/_cyclic_import_package/yaml.py
import_watch-2.0.1.dist-info/METADATA
import_watch-2.0.1.dist-info/WHEEL
import_watch-2.0.1.dist-info/top_level.txt
import_watch-2.0.1.dist-info/RECORD
