Metadata-Version: 2.1
Name: import-watch
Version: 2.0.1
Summary: Trace module imports and detect/deny cyclic imports at runtime
Home-page: https://github.com/hartwork/import-watch
Author: Sebastian Pipping
Author-email: sebastian@pipping.org
License: MIT
Platform: UNKNOWN
Classifier: Development Status :: 3 - Alpha
Classifier: Intended Audience :: Developers
Classifier: License :: OSI Approved :: MIT License
Classifier: Natural Language :: English
Classifier: Programming Language :: Python :: 2.7
Classifier: Programming Language :: Python :: 3.5
Classifier: Programming Language :: Python :: 3.6
Classifier: Programming Language :: Python :: 3.7
Classifier: Programming Language :: Python :: 3.8
Classifier: Programming Language :: Python :: Implementation :: CPython
